termiipython/__init__.py
termiipython/auth.py
termiipython/campaign.py
termiipython/contacts.py
termiipython/endpoints/__Init__.py
termiipython/endpoints/campaign.py
termiipython/endpoints/contacts.py
termiipython/endpoints/messaging.py
termiipython/endpoints/token.py
termiipython/messaging.py
termiipython/schemas/__init__.py
termiipython/schemas/messaging.py
termiipython/schemas/shared.py
termiipython/schemas/token.py
termiipython/token.py
termiipython/utils.py
termiipython-3.0.0.dist-info/LICENSE
termiipython-3.0.0.dist-info/METADATA
termiipython-3.0.0.dist-info/WHEEL
termiipython-3.0.0.dist-info/RECORD
