Metadata-Version: 2.1
Name: termiipython
Version: 3.0.0
Summary: Termii Python Library for Termii API
License: MIT
Author: Solomon Olatunji
Requires-Python: >=3.9,<4.0
Classifier: License :: OSI Approved :: MIT License
Classifier: Programming Language :: Python :: 3
Classifier: Programming Language :: Python :: 3.9
Classifier: Programming Language :: Python :: 3.10
Classifier: Programming Language :: Python :: 3.11
Classifier: Programming Language :: Python :: 3.12
Requires-Dist: pydantic (>=1.10.4,<=2.5.0)
Requires-Dist: requests (>=2.23.0,<=2.31.0)
